ada_genai.py
ada_genai-0.0.1.dist-info/METADATA
ada_genai-0.0.1.dist-info/WHEEL
ada_genai-0.0.1.dist-info/top_level.txt
ada_genai-0.0.1.dist-info/RECORD
