Metadata-Version: 2.1
Name: ada-genai
Version: 0.0.1
Summary: pending
Author-email: michael <michael_chia7@msn.com>
